libarchive/__init__.py
libarchive/entry.py
libarchive/exception.py
libarchive/extract.py
libarchive/ffi.py
libarchive/flags.py
libarchive/read.py
libarchive/write.py
libarchive_c-4.0.dist-info/LICENSE.md
libarchive_c-4.0.dist-info/METADATA
libarchive_c-4.0.dist-info/WHEEL
libarchive_c-4.0.dist-info/top_level.txt
libarchive_c-4.0.dist-info/RECORD
