Metadata-Version: 2.1
Name: libarchive-c
Version: 4.0
Summary: Python interface to libarchive
Home-page: https://github.com/Changaco/python-libarchive-c
Author: Changaco
Author-email: changaco@changaco.oy.lc
License: CC0
Keywords: archive libarchive 7z tar bz2 zip gz
Platform: UNKNOWN
License-File: LICENSE.md
